imagetyperz/__init__.py
imagetyperz/auth.py
imagetyperz/client.py
imagetyperz/constants.py
imagetyperz/exceptions.py
imagetyperz/util/__init__.py
imagetyperz/util/logging.py
imagetyperz_async-0.3.2.dist-info/WHEEL
imagetyperz_async-0.3.2.dist-info/LICENSE
imagetyperz_async-0.3.2.dist-info/METADATA
imagetyperz_async-0.3.2.dist-info/RECORD
