Metadata-Version: 2.1
Name: imagetyperz-async
Version: 0.3.2
Summary: Asynchronous client for the ImageTyperz API
Home-page: https://github.com/theY4Kman/imagetyperz-async
License: MIT
Keywords: imagetyperz,captcha
Author: Zach "theY4Kman" Kanzler
Author-email: they4kman@gmail.com
Requires-Python: >=3.6,<4.0
Classifier: Development Status :: 4 - Beta
Classifier: Intended Audience :: Developers
Classifier: Intended Audience :: Information Technology
Classifier: License :: OSI Approved :: MIT License
Classifier: Programming Language :: Python :: 3
Classifier: Programming Language :: Python :: 3.6
Classifier: Programming Language :: Python :: 3.7
Classifier: Programming Language :: Python :: 3.8
Classifier: Programming Language :: Python :: 3.9
Classifier: Programming Language :: Python :: 3.10
Classifier: Programming Language :: Python :: 3.11
Classifier: Topic :: Internet :: WWW/HTTP
Requires-Dist: httpx (>=0.15.0)
